odoo/addons/account_journal_restrict_mode/README.rst
odoo/addons/account_journal_restrict_mode/__init__.py
odoo/addons/account_journal_restrict_mode/__manifest__.py
odoo/addons/account_journal_restrict_mode/hooks.py
odoo/addons/account_journal_restrict_mode/i18n/account_journal_restrict_mode.pot
odoo/addons/account_journal_restrict_mode/i18n/es.po
odoo/addons/account_journal_restrict_mode/i18n/it.po
odoo/addons/account_journal_restrict_mode/models/__init__.py
odoo/addons/account_journal_restrict_mode/models/account_journal.py
odoo/addons/account_journal_restrict_mode/readme/CONTRIBUTORS.rst
odoo/addons/account_journal_restrict_mode/readme/DESCRIPTION.rst
odoo/addons/account_journal_restrict_mode/readme/ROADMAP.rst
odoo/addons/account_journal_restrict_mode/static/description/icon.png
odoo/addons/account_journal_restrict_mode/static/description/index.html
odoo/addons/account_journal_restrict_mode/tests/__init__.py
odoo/addons/account_journal_restrict_mode/tests/test_account_journal_restrict_mode.py
odoo13_addon_account_journal_restrict_mode-13.0.1.0.1.dev3.dist-info/METADATA
odoo13_addon_account_journal_restrict_mode-13.0.1.0.1.dev3.dist-info/WHEEL
odoo13_addon_account_journal_restrict_mode-13.0.1.0.1.dev3.dist-info/top_level.txt
odoo13_addon_account_journal_restrict_mode-13.0.1.0.1.dev3.dist-info/RECORD
