Metadata-Version: 2.1
Name: odoo13-addon-account_journal_restrict_mode
Version: 13.0.1.0.1.dev3
Summary: Lock All Posted Entries of Journals.
Home-page: https://github.com/OCA/account-financial-tools
Author: ForgeFlow S.L., Odoo Community Association (OCA)
Author-email: support@odoo-community.org
License: AGPL-3
Classifier: Programming Language :: Python
Classifier: Framework :: Odoo
Classifier: Framework :: Odoo :: 13.0
Classifier: License :: OSI Approved :: GNU Affero General Public License v3
Requires-Python: >=3.5
Requires-Dist: odoo<13.1dev,>=13.0a
